bleak_py-0.1.20.dist-info/METADATA
bleak_py-0.1.20.dist-info/WHEEL
bleak_py-0.1.20.dist-info/licenses/LICENSE
bleak_py.libs/libattr-4f2a9577.so.1
bleak_py.libs/libbz2-a273e504.so.1
bleak_py.libs/libcap-79733b59.so.2
bleak_py.libs/libdbus-1-5d678da9.so.3
bleak_py.libs/libdw-780627ce.so.1
bleak_py.libs/libelf-3d9de92a.so.1
bleak_py.libs/libgcrypt-18957bae.so.11
bleak_py.libs/libgpg-error-3f09c3c7.so.0
bleak_py.libs/liblz4-af1653fb.so.1
bleak_py.libs/liblzma-004595ca.so.5
bleak_py.libs/libpcre-9513aab5.so.1
bleak_py.libs/libselinux-0922c95c.so.1
bleak_py.libs/libsystemd-7fd64813.so.0
bleak_py/__init__.py
bleak_py/__init__.pyi
bleak_py/bleak_py.cpython-312-x86_64-linux-gnu.so
bleak_py-0.1.20.dist-info/RECORD
