Metadata-Version: 2.4
Name: bleak-py
Version: 0.1.20
License-File: LICENSE
Summary: A cross-platform BLE library based on btleplug.
Home-Page: https://github.com/jesses2025smith/bleak-rs
Author: Jesse Smith
License: MIT
Requires-Python: >=3.9
Project-URL: homepage, https://github.com/jesses2025smith/bleak-rs/tree/py
Project-URL: repository, https://github.com/jesses2025smith/bleak-rs
